nxmodbus/__init__.py
nxmodbus/addresses.py
nxmodbus/client_rtu.py
nxmodbus/client_tcp.py
nxmodbus/proptypes.py
nxmodbus-0.3.0.dist-info/LICENSE
nxmodbus-0.3.0.dist-info/METADATA
nxmodbus-0.3.0.dist-info/WHEEL
nxmodbus-0.3.0.dist-info/top_level.txt
nxmodbus-0.3.0.dist-info/RECORD
