Metadata-Version: 2.1
Name: nxmodbus
Version: 0.3.0
Summary: Package that let easily interact with the Next devices over Modbus RTU
Home-page: https://github.com/studer-innotec/next-modbus
Author: Studer Innotec SA
Author-email: develop@studer-innotec.com
Maintainer-email: develop@studer-innotec.com
License: MIT
Project-URL: Documentation, https://nxmodbus.readthedocs.io/en/latest/index.html
Project-URL: Issues tracker, https://github.com/studer-innotec/next-modbus/issues
Project-URL: Source Code, https://github.com/studer-innotec/next-modbus
Classifier: Programming Language :: Python :: 3
Classifier: License :: OSI Approved :: MIT License
Classifier: Operating System :: OS Independent
Classifier: Development Status :: 4 - Beta
Classifier: Topic :: Communications
Classifier: Topic :: Software Development :: Libraries
Classifier: Topic :: Software Development :: Libraries :: Python Modules
Requires-Python: >=3.6.8
License-File: LICENSE
Requires-Dist: uModbus==1.0.3
Requires-Dist: pyserial>=3.4
Requires-Dist: pyModbusTCP==0.1.10
